sept_qt/__init__.py
sept_qt/_version.py
sept_qt/documentation_widget.py
sept_qt/file_input_widget.py
sept_qt/input_widget.py
sept_qt/preview_widget.py
sept_qt-0.2.3.dist-info/METADATA
sept_qt-0.2.3.dist-info/WHEEL
sept_qt-0.2.3.dist-info/top_level.txt
sept_qt-0.2.3.dist-info/RECORD
